Metadata-Version: 2.1
Name: CsPy-Uploading
Version: 1.0.11
Summary: Package useful for THG staff to aid data pipeline implementation
Home-page: https://github.com/JamesRobinson-THG/CsPy_Uploading/archive/1.0.11.tar.gz
Author: James Robinson
Author-email: james.robinson@thehutgroup.com
License: UNKNOWN
Platform: UNKNOWN
Classifier: Development Status :: 3 - Alpha
Classifier: Programming Language :: Python :: 3
Classifier: License :: OSI Approved :: MIT License
Classifier: Operating System :: OS Independent
Requires-Python: >=3.9
